MANIFEST.in
README.rst
setup.py
simple_site_checker.py
SimpleSiteChecker.egg-info/PKG-INFO
SimpleSiteChecker.egg-info/SOURCES.txt
SimpleSiteChecker.egg-info/dependency_links.txt
SimpleSiteChecker.egg-info/requires.txt
SimpleSiteChecker.egg-info/top_level.txt