Metadata-Version: 1.0
Name: SimpleSiteChecker
Version: 0.1.03
Summary: Simple Site Checker is a command line tool that allows you to run a website pages check using XML sitemap
Home-page: http://pypi.python.org/pypi/SimpleSiteChecker/
Author: Ilian Iliev
Author-email: ilian@i-n-i.org
License: LICENSE
Platform: UNKNOWN
